Metadata-Version: 1.1
Name: stacking
Version: 0.1.2
Summary: A stacking library for ensemble learning
Home-page: https://github.com/ikki407/stacking
Author: Ikki Tanaka
Author-email: ikki0407@gmail.com
License: MIT
Keywords: stacking,ensemble,machine learning,cross validation,sckit-learn,XGBoost,Keras,Vowpal Wabbit
Platform: UNKNOWN
Classifier: Development Status :: 3 - Alpha
Classifier: Environment :: Console
Classifier: Intended Audience :: Science/Research
Classifier: Natural Language :: English
Classifier: Operating System :: OS Independent
Classifier: Programming Language :: Python
Classifier: Topic :: Scientific/Engineering
Classifier: Topic :: Scientific/Engineering :: Artificial Intelligence
Classifier: Topic :: Utilities
Classifier: License :: OSI Approved :: MIT License
